aizynthfinder/__init__.py
aizynthfinder/aizynthfinder.py
aizynthfinder/analysis/__init__.py
aizynthfinder/analysis/routes.py
aizynthfinder/analysis/tree_analysis.py
aizynthfinder/analysis/utils.py
aizynthfinder/chem/__init__.py
aizynthfinder/chem/mol.py
aizynthfinder/chem/reaction.py
aizynthfinder/chem/serialization.py
aizynthfinder/context/__init__.py
aizynthfinder/context/collection.py
aizynthfinder/context/config.py
aizynthfinder/context/policy/__init__.py
aizynthfinder/context/policy/expansion_strategies.py
aizynthfinder/context/policy/filter_strategies.py
aizynthfinder/context/policy/policies.py
aizynthfinder/context/policy/utils.py
aizynthfinder/context/scoring/__init__.py
aizynthfinder/context/scoring/collection.py
aizynthfinder/context/scoring/scorers.py
aizynthfinder/context/scoring/scorers_base.py
aizynthfinder/context/scoring/scorers_mols.py
aizynthfinder/context/scoring/scorers_reactions.py
aizynthfinder/context/stock/__init__.py
aizynthfinder/context/stock/queries.py
aizynthfinder/context/stock/stock.py
aizynthfinder/data/default_training.yml
aizynthfinder/data/logging.yml
aizynthfinder/data/templates/reaction_tree.dot
aizynthfinder/data/templates/reaction_tree.thtml
aizynthfinder/interfaces/__init__.py
aizynthfinder/interfaces/aizynthapp.py
aizynthfinder/interfaces/aizynthcli.py
aizynthfinder/interfaces/gui/__init__.py
aizynthfinder/interfaces/gui/clustering.py
aizynthfinder/interfaces/gui/pareto_fronts.py
aizynthfinder/interfaces/gui/utils.py
aizynthfinder/reactiontree.py
aizynthfinder/search/__init__.py
aizynthfinder/search/andor_trees.py
aizynthfinder/search/breadth_first/__init__.py
aizynthfinder/search/breadth_first/nodes.py
aizynthfinder/search/breadth_first/search_tree.py
aizynthfinder/search/dfpn/__init__.py
aizynthfinder/search/dfpn/nodes.py
aizynthfinder/search/dfpn/search_tree.py
aizynthfinder/search/mcts/__init__.py
aizynthfinder/search/mcts/node.py
aizynthfinder/search/mcts/search.py
aizynthfinder/search/mcts/state.py
aizynthfinder-4.4.1.dist-info/METADATA
aizynthfinder-4.4.1.dist-info/WHEEL
aizynthfinder-4.4.1.dist-info/entry_points.txt
aizynthfinder-4.4.1.dist-info/licenses/LICENSE
aizynthfinder-4.4.1.dist-info/RECORD
