Metadata-Version: 2.4
Name: aizynthfinder
Version: 4.4.1
Summary: Retrosynthetic route finding using neural network guided Monte-Carlo tree search
License: MIT
License-File: LICENSE
Author: Molecular AI group
Author-email: samuel.genheden@astrazeneca.com
Requires-Python: >=3.10,<3.13
Classifier: License :: OSI Approved :: MIT License
Classifier: Programming Language :: Python :: 3
Classifier: Programming Language :: Python :: 3.10
Classifier: Programming Language :: Python :: 3.11
Classifier: Programming Language :: Python :: 3.12
Provides-Extra: all
Provides-Extra: tf
Requires-Dist: dask (>=2024.4.1)
Requires-Dist: deprecated (>=1.2.10,<2.0.0)
Requires-Dist: grpcio (>=1.24.0,<2.0.0) ; extra == "tf"
Requires-Dist: ipywidgets (>=7.5.1,<8.0.0)
Requires-Dist: jinja2 (>=3.0.0,<4.0.0)
Requires-Dist: jupyter (>=1.0.0,<2.0.0)
Requires-Dist: jupytext (>=1.3.3,<2.0.0)
Requires-Dist: matplotlib (>=3.0.0,<4.0.0)
Requires-Dist: molbloom (>=2.1.0,<3.0.0) ; extra == "all"
Requires-Dist: networkx (>=2.4,<3.0)
Requires-Dist: notebook (>=6.5.3,<7.0.0)
Requires-Dist: numpy (<2.0.0)
Requires-Dist: onnxruntime (>=1.23.0,<2.0.0)
Requires-Dist: pandas (>=1.0.0,<3.0.0)
Requires-Dist: paretoset (>=1.2.3,<2.0.0)
Requires-Dist: pillow (>=12.0.0,<13.0.0)
Requires-Dist: pymongo (>=3.10.1,<4.0.0) ; extra == "all"
Requires-Dist: rdchiral (>=1.0.0,<2.0.0)
Requires-Dist: rdkit (>=2023.9.1,<2024.0.0)
Requires-Dist: reaction-utils (>=1.9.3,<2.0.0)
Requires-Dist: requests (>=2.23.0,<3.0.0)
Requires-Dist: route-distances (>=1.2.4,<2.0.0) ; extra == "all"
Requires-Dist: scipy (>=1.0,<2.0) ; extra == "all"
Requires-Dist: seaborn (>=0.13.2,<0.14.0)
Requires-Dist: tables (>=3.6.1,<4.0.0)
Requires-Dist: tensorflow (>=2.20.0,<3.0.0) ; extra == "tf"
Requires-Dist: tensorflow-serving-api (>=2.1.0,<3.0.0) ; extra == "tf"
Requires-Dist: timeout-decorator (>=0.5.0,<0.6.0) ; extra == "all"
Requires-Dist: tqdm (>=4.42.1,<5.0.0)
Project-URL: Documentation, https://molecularai.github.io/aizynthfinder/
Project-URL: Homepage, https://github.com/MolecularAI/aizynthfinder/
Project-URL: Repository, https://github.com/MolecularAI/aizynthfinder/
